nextconsole/__init__.py
nextconsole/command.py
nextconsole/envinfo.py
nextconsole-0.0.20.dist-info/METADATA
nextconsole-0.0.20.dist-info/WHEEL
nextconsole-0.0.20.dist-info/entry_points.txt
nextconsole-0.0.20.dist-info/top_level.txt
nextconsole-0.0.20.dist-info/RECORD
