Metadata-Version: 2.1
Name: nextconsole
Version: 0.0.20
Summary: nextconsole
Home-page: https://github.com/hp027/nextconsole
Author: hp027
Author-email: hp027@foxmail.com
License: UNKNOWN
Platform: UNKNOWN
Classifier: Programming Language :: Python :: 3
Classifier: License :: OSI Approved :: MIT License
Classifier: Operating System :: OS Independent
Requires-Python: >=3.6
Requires-Dist: flask
Requires-Dist: requests
Requires-Dist: rich
Requires-Dist: wcwidth
